publishable/__init__.py
publishable/admin.py
publishable/apps.py
publishable/constants.py
publishable/context_managers.py
publishable/managers.py
publishable/models.py
publishable/utils.py
publishable/migrations/0001_initial.py
publishable/migrations/0002_auto_20190128_1303.py
publishable/migrations/__init__.py
django_publishable-0.1.13.dist-info/LICENSE
django_publishable-0.1.13.dist-info/METADATA
django_publishable-0.1.13.dist-info/WHEEL
django_publishable-0.1.13.dist-info/top_level.txt
django_publishable-0.1.13.dist-info/RECORD
