Metadata-Version: 2.1
Name: django-publishable
Version: 0.1.13
Summary: A simple Django app to add draft/publish capabilities to your models.
Home-page: https://github.com/Ilyes-Hammadi/django-publishable
Author: Ilyes Hammadi
Author-email: hammadiilyesahmed@gmail.com
License: Apache Software License
Platform: UNKNOWN
Classifier: Environment :: Web Environment
Classifier: Framework :: Django
Classifier: Framework :: Django :: 1.11
Classifier: License :: OSI Approved :: Apache Software License
Classifier: Programming Language :: Python :: 2.7
Classifier: Programming Language :: Python :: 3.6
